{
  "order_size": [
    {
      "id_size": 1,
      "name": "120*60*18"
    },
    {
      "id_size": 2,
      "name": "125*65*18"
    },
    {
      "id_size": 3,
      "name": "140*70*18"
    },
    {
      "id_size": 4,
      "name": "160*70*18"
    },
    {
      "id_size": 5,
      "name": "180*80*18"
    },
    {
      "id_size": 6,
      "name": "180*90*18"
    },
    {
      "id_size": 7,
      "name": "200(190)*80*18"
    },
    {
      "id_size": 8,
      "name": "200(190)*90*18"
    }
  ]
}